README.md
setup.cfg
setup.py
amplot/__init__.py
amplot/amplot.py
amplot/color_dicts.py
amplot/mass_marker.py
amplot.egg-info/PKG-INFO
amplot.egg-info/SOURCES.txt
amplot.egg-info/dependency_links.txt
amplot.egg-info/requires.txt
amplot.egg-info/top_level.txt