Metadata-Version: 1.0
Name: amplot
Version: 0.3.0
Summary: A map plot based on Amap(高德地图).
Home-page: https://github.com/KECB/amplot
Author: Yang Bai
Author-email: by66666@gmail.com
License: MIT
Keywords: amplot,map,plot
Platform: UNKNOWN
